strapvizpy/__init__.py
strapvizpy/bootstrap.py
strapvizpy/display.py
strapvizpy-0.2.4.dist-info/LICENSE
strapvizpy-0.2.4.dist-info/WHEEL
strapvizpy-0.2.4.dist-info/METADATA
strapvizpy-0.2.4.dist-info/RECORD
