Metadata-Version: 2.1
Name: strapvizpy
Version: 0.2.4
Summary: Performs bootstrapping of a dataset to produce plots and statistics for use in final reports and documents. 
License: MIT
Author: Julien Gordon, Gautham Pughazhendhi, Zack Tang, Margot Vore
Requires-Python: >=3.9,<4.0
Classifier: License :: OSI Approved :: MIT License
Classifier: Programming Language :: Python :: 3
Classifier: Programming Language :: Python :: 3.10
Classifier: Programming Language :: Python :: 3.9
Requires-Dist: lxml (>=4.7.1,<5.0.0)
Requires-Dist: matplotlib (>=3.5.1,<4.0.0)
Requires-Dist: numpy (>=1.22.1,<2.0.0)
Requires-Dist: pandas (>=1.4.0,<2.0.0)
